py_sne_rest_client/SpirentNetworkEmulator.py
py_sne_rest_client/__init__.py
py_sne_rest_client-0.2.dist-info/LICENSE
py_sne_rest_client-0.2.dist-info/METADATA
py_sne_rest_client-0.2.dist-info/WHEEL
py_sne_rest_client-0.2.dist-info/top_level.txt
py_sne_rest_client-0.2.dist-info/zip-safe
py_sne_rest_client-0.2.dist-info/RECORD
